PyBittrex-1.0.0.dist-info/DESCRIPTION.rst
PyBittrex-1.0.0.dist-info/METADATA
PyBittrex-1.0.0.dist-info/RECORD
PyBittrex-1.0.0.dist-info/WHEEL
PyBittrex-1.0.0.dist-info/metadata.json
PyBittrex-1.0.0.dist-info/top_level.txt
pybittrex/__init__.py
pybittrex/auth.py
pybittrex/client.py
pybittrex/setup.py
