Metadata-Version: 2.0
Name: PyBittrex
Version: 1.0.0
Summary: Library for Bittrex API
Home-page: https://github.com/mattselph/pybittrex
Author: Matt Selph
Author-email: mattselph@outlook.com
License: MIT
Keywords: bittrex bitcoin ethereum cryptocurrency trading
Platform: UNKNOWN
Classifier: Development Status :: 5 - Production/Stable
Classifier: Intended Audience :: Developers
Classifier: License :: OSI Approved :: MIT License
Classifier: Operating System :: OS Independent
Classifier: Topic :: Software Development :: Libraries :: Python Modules
Classifier: Programming Language :: Python :: 2
Classifier: Programming Language :: Python :: 2.7
Classifier: Programming Language :: Python :: 3
Classifier: Programming Language :: Python :: 3.2
Classifier: Programming Language :: Python :: 3.3
Classifier: Programming Language :: Python :: 3.4
Classifier: Programming Language :: Python :: 3.5
Classifier: Programming Language :: Python :: 3.6
Requires-Dist: requests
